analystock_api/__init__.py
analystock_api/basis.py
analystock_api/earnings.py
analystock_api/fundamental.py
analystock_api/market_data.py
analystock_api/query_generic.py
analystock_api/screener.py
analystock_ai-0.1.7.dist-info/LICENSE
analystock_ai-0.1.7.dist-info/METADATA
analystock_ai-0.1.7.dist-info/WHEEL
analystock_ai-0.1.7.dist-info/top_level.txt
analystock_ai-0.1.7.dist-info/RECORD
