Metadata-Version: 2.1
Name: analystock-ai
Version: 0.1.7
Summary: Public client API for Analystock.ai REST API
Home-page: https://github.com/ahgperrin/analystock-api
Author: Antoine Perrin
Author-email: antoine.perrin@analystock.ai
License: UNKNOWN
Platform: UNKNOWN
Classifier: Programming Language :: Python :: 3.9
Classifier: License :: OSI Approved :: MIT License
Classifier: Operating System :: OS Independent
Requires-Python: >=3.6
Requires-Dist: requests
